pytest_astropy_header/__init__.py
pytest_astropy_header/display.py
pytest_astropy_header/version.py
pytest_astropy_header-0.2.2.dist-info/LICENSE.rst
pytest_astropy_header-0.2.2.dist-info/METADATA
pytest_astropy_header-0.2.2.dist-info/WHEEL
pytest_astropy_header-0.2.2.dist-info/entry_points.txt
pytest_astropy_header-0.2.2.dist-info/top_level.txt
pytest_astropy_header-0.2.2.dist-info/RECORD
