Metadata-Version: 2.1
Name: pytest-astropy-header
Version: 0.2.2
Summary: pytest plugin to add diagnostic information to the header of the test output
Home-page: https://github.com/astropy/pytest-astropy-header
Author: The Astropy Developers
Author-email: astropy.team@gmail.com
License: BSD 3-Clause License
Classifier: Development Status :: 3 - Alpha
Classifier: Intended Audience :: Developers
Classifier: Programming Language :: Python :: 3 :: Only
Classifier: Programming Language :: Python :: 3.7
Classifier: Programming Language :: Python :: 3.8
Classifier: Programming Language :: Python :: 3.9
Classifier: Programming Language :: Python :: 3.10
Classifier: Operating System :: OS Independent
Classifier: License :: OSI Approved :: BSD License
Requires-Python: >=3.7
Provides-Extra: test
License-File: LICENSE.rst
